LICENSE
MANIFEST.in
README.rst
setup.py
class_based_auth_views/__init__.py
class_based_auth_views/forms.py
class_based_auth_views/utils.py
class_based_auth_views/version.py
class_based_auth_views/views.py
django_class_auth_views.egg-info/PKG-INFO
django_class_auth_views.egg-info/SOURCES.txt
django_class_auth_views.egg-info/dependency_links.txt
django_class_auth_views.egg-info/not-zip-safe
django_class_auth_views.egg-info/top_level.txt