Metadata-Version: 1.1
Name: django-class-auth-views
Version: 1.0.0
Summary: A reimplementation of django.contrib.auth.views as class based views.
Home-page: https://github.com/druids/django-class-based-auth-views
Author: Stefan Foulis
Author-email: stefan@foulis.ch
License: BSD
Platform: OS Independent
Classifier: Development Status :: 3 - Alpha
Classifier: Framework :: Django
Classifier: Intended Audience :: Developers
Classifier: License :: OSI Approved :: BSD License
Classifier: Operating System :: OS Independent
Classifier: Programming Language :: Python
Classifier: Topic :: Internet :: WWW/HTTP
